fit_testcase_sender/__init__.py
fit_testcase_sender/func.py
fit_testcase_sender/remote.py
FIT_Testcase_Sender-1.0.0.dist-info/METADATA
FIT_Testcase_Sender-1.0.0.dist-info/WHEEL
FIT_Testcase_Sender-1.0.0.dist-info/top_level.txt
FIT_Testcase_Sender-1.0.0.dist-info/RECORD
