Metadata-Version: 2.1
Name: FIT_Testcase_Sender
Version: 1.0.0
Summary: A utility for sending scenarios via TCP/IP and checking their completion
Author: suresofttech
Author-email: sdhan@suresofttch.com
License: MIT
Classifier: Programming Language :: Python :: 3
Classifier: License :: OSI Approved :: MIT License
Requires-Python: >=3.6
